{
    "reviews": [
        {
            "autor_name": "JULIO BAEZA",
            "autor_image": "https://lh3.googleusercontent.com/a-/ALV-UjVYPKXRLjpbDXDBeGQH735ZgMM9OMsCSC9CXCh9mEh53QKFbGs1Iw=s120-c-rp-mo-ba3-br100",
            "review_text": "Excelente!!! Un lugar de sue침os , caba침a rodeada de 치rboles frutales!! La atenci칩n excelente!!",
            "review_link": "https://www.google.com/maps/reviews/data=!4m8!14m7!1m6!2m5!1sCi9DQUlRQUNvZENodHljRjlvT2tsNVNXOTVVa3g2ZWpZMWJtZElhbTlETVUxcU9YYxAB!2m1!1s0x0:0xe7f57694b5338ff2!3m1!1s2@1:CAIQACodChtycF9oOkl5SW95Ukx6ejY1bmdIam9DMU1qOXc%7C0dW-wEkOX9K%7C?hl=en",
            "review_rating": "5",
            "review_date": "05/02/2026"
        },
        {
            "autor_name": "Jorge Arias",
            "autor_image": "https://lh3.googleusercontent.com/a/ACg8ocL9-kuxNz03qx4FpsJcojzILhui-k59CsiiU8-2r1sLADYAJg=s120-c-rp-mo-ba3-br100",
            "review_text": "La caba침a con todo lo que puedas necesitar, buena ubicacion y muy tranquilo, el due침o muy atento, una excelente opci칩n para descansar, seguro volveremos a elegirlos.",
            "review_link": "https://www.google.com/maps/reviews/data=!4m8!14m7!1m6!2m5!1sCi9DQUlRQUNvZENodHljRjlvT2pKb05sUjVTREZYZEZNNGNtMUtlRmhaVmxoeloxRRAB!2m1!1s0x0:0xe7f57694b5338ff2!3m1!1s2@1:CAIQACodChtycF9oOjJoNlR5SDFXdFM4cm1KeFhZVlhzZ1E%7C0dVtQCNK0Ct%7C?hl=en",
            "review_rating": "5",
            "review_date": "04/02/2026"
        },
        {
            "autor_name": "Clau Coya",
            "autor_image": "https://lh3.googleusercontent.com/a/ACg8ocLUkcSr1hm01IrCPqXhxlJQ-FHclSOKIb2D8l1V5ROCo3DrPw=s120-c-rp-mo-br100",
            "review_text": "Muy linda y c칩moda la caba침a, el lugar donde est치 ubicada es muy tranquilo y bello, muy cerca del lago.",
            "review_link": "https://www.google.com/maps/reviews/data=!4m8!14m7!1m6!2m5!1sCi9DQUlRQUNvZENodHljRjlvT2pSTlRtRmpkVEJIZDNGclZYVTBhbWQ1WDI5WlkwRRAB!2m1!1s0x0:0xe7f57694b5338ff2!3m1!1s2@1:CAIQACodChtycF9oOjRNTmFjdTBHd3FrVXU0amd5X29ZY0E%7C0dTw7aCIgw7%7C?hl=en",
            "review_rating": "5",
            "review_date": "29/01/2026"
        },
        {
            "autor_name": "Eliana Maiolino",
            "autor_image": "https://lh3.googleusercontent.com/a-/ALV-UjUATo2RVQ3PY4myYpqPgEujR_hAs_f_-FlaFTZoQAASlKxnmSvMXw=s120-c-rp-mo-ba2-br100",
            "review_text": "Hermosa caba침a! Excelente atenci칩n!\nNos quedamos con ganas de quedarnos muchos d칤as m치s!",
            "review_link": "https://www.google.com/maps/reviews/data=!4m8!14m7!1m6!2m5!1sCi9DQUlRQUNvZENodHljRjlvT25KTmVXaGlRM1YyVGxSTmNUSmtSMG93TTFsRk5VRRAB!2m1!1s0x0:0xe7f57694b5338ff2!3m1!1s2@1:CAIQACodChtycF9oOnJNeWhiQ3V2TlRNcTJkR0owM1lFNUE%7C0dP4_zDrtjG%7C?hl=en",
            "review_rating": "5",
            "review_date": "15/01/2026"
        },
        {
            "autor_name": "Gerardo Rodriguez",
            "autor_image": "https://lh3.googleusercontent.com/a/ACg8ocLVRZmb6dENc5J-_ZfpvJ7IsXEVIcI_GeV0684xqy8TEm583A=s120-c-rp-mo-br100",
            "review_text": "Est치bamos muy cerca del lago, el r칤o, la catarata y paseo a pie. La caba침a super limpia, ordenada y completo con todo lo necesario. Un lugar para descansar con un patio hermoso y con estacionamiento. Recomendable 100%.",
            "review_link": "https://www.google.com/maps/reviews/data=!4m8!14m7!1m6!2m5!1sCi9DQUlRQUNvZENodHljRjlvT2pobWFYSTJNVlZRZGswMWJVcExWVmhsT0Zvd01HYxAB!2m1!1s0x0:0xe7f57694b5338ff2!3m1!1s2@1:CAIQACodChtycF9oOjhmaXI2MVVQdk01bUpLVVhlOFowMGc%7C0dNaD3hQ7wQ%7C?hl=en",
            "review_rating": "5",
            "review_date": "10/01/2026"
        },
        {
            "autor_name": "Agrim. Walter Rodriguez",
            "autor_image": "https://lh3.googleusercontent.com/a-/ALV-UjW9jjU-MWLKakjtxb4NvXKfVR7IOQjtRaGu-fNYVa9E46W7bo5T=s120-c-rp-mo-br100",
            "review_text": "Gracias por todo!!",
            "review_link": "https://www.google.com/maps/reviews/data=!4m8!14m7!1m6!2m5!1sCi9DQUlRQUNvZENodHljRjlvT2tGVVJVTm9ZMGxDUVVWSVkzSk1SVzFSUTJaM05uYxAB!2m1!1s0x0:0xe7f57694b5338ff2!3m1!1s2@1:CAIQACodChtycF9oOkFURUNoY0lCQUVIY3JMRW1RQ2Z3Nnc%7C0dMKzS8q8OW%7C?hl=en",
            "review_rating": "5",
            "review_date": "06/01/2026"
        },
        {
            "autor_name": "Walter Romero",
            "autor_image": "https://lh3.googleusercontent.com/a/ACg8ocJxcl6595zKMWfTRjDWox_RDzmtJ8esF96LU3k2geDq9kfB=s120-c-rp-mo-br100",
            "review_text": "La caba침a muy c칩moda y la atenci칩n del due침o es excelente",
            "review_link": "https://www.google.com/maps/reviews/data=!4m8!14m7!1m6!2m5!1sCi9DQUlRQUNvZENodHljRjlvT21NMlpVbE1lQzA1ZVZoMGNVUmpWMDQ1ZEdGdVNGRRAB!2m1!1s0x0:0xe7f57694b5338ff2!3m1!1s2@1:CAIQACodChtycF9oOmM2ZUlMeC05eVh0cURjV045dGFuSFE%7C0dLIGlDTTGH%7C?hl=en",
            "review_rating": "5",
            "review_date": "03/01/2026"
        },
        {
            "autor_name": "Gabriela Lopez Robledo",
            "autor_image": "https://lh3.googleusercontent.com/a/ACg8ocIE96VA4mN69FKSfbEVdd-Y95XRQhCXEV93JGmFT9-HIcvToQ=s120-c-rp-mo-br100",
            "review_text": "La caba침a muy c칩moda y excelente atenci칩n del due침o!",
            "review_link": "https://www.google.com/maps/reviews/data=!4m8!14m7!1m6!2m5!1sCi9DQUlRQUNvZENodHljRjlvT21OQ1IwNXJWVWxzUTB0U1RFTm9XRkpOTkdORVkwRRAB!2m1!1s0x0:0xe7f57694b5338ff2!3m1!1s2@1:CAIQACodChtycF9oOmNCR05rVUlsQ0tSTENoWFJNNGNEY0E%7C0dLIGYTP8Ar%7C?hl=en",
            "review_rating": "5",
            "review_date": "03/01/2026"
        },
        {
            "autor_name": "reynaldo colombatti",
            "autor_image": "https://lh3.googleusercontent.com/a-/ALV-UjXbhQ72FYC0T54tut2FUzUKa_5oUp8HzoiwZcgELXOSwpidvOk=s120-c-rp-mo-ba3-br100",
            "review_text": "Excelente lugar. Muy buena la calidad de las caba침as. Muy buena ubicaci칩n. La due침a estuvo siempre atenta.",
            "review_link": "https://www.google.com/maps/reviews/data=!4m8!14m7!1m6!2m5!1sCi9DQUlRQUNvZENodHljRjlvT2tWRU5VNXpTemx2TlRCNlowUkdWRzFIU0VaR1VWRRAB!2m1!1s0x0:0xe7f57694b5338ff2!3m1!1s2@1:CAIQACodChtycF9oOkVENU5zSzlvNTB6Z0RGVG1HSEZGUVE%7C0dJvWsvTmhP%7C?hl=en",
            "review_rating": "5",
            "review_date": "30/12/2025"
        },
        {
            "autor_name": "Roxana Millapan",
            "autor_image": "https://lh3.googleusercontent.com/a/ACg8ocI5Jk3tgsaVMeE-yVa8SkLtHSixkjjVk73u1J_4jZQB97TIhQ=s120-c-rp-mo-br100",
            "review_text": "El lugar es precioso , muy c칩modo y tranquilo justo lo que busc치bamos para pasar la navidad... Agradecidos con el anfitri칩n...",
            "review_link": "https://www.google.com/maps/reviews/data=!4m8!14m7!1m6!2m5!1sCi9DQUlRQUNvZENodHljRjlvT21reVFsQlBUblUyUm1SVVMwRnFTazlmZDB4SGFuYxAB!2m1!1s0x0:0xe7f57694b5338ff2!3m1!1s2@1:CAIQACodChtycF9oOmkyQlBPTnU2RmRUS0FqSk9fd0xHanc%7C0dJHh-GAK2R%7C?hl=en",
            "review_rating": "5",
            "review_date": "28/12/2025"
        },
        {
            "autor_name": "Mariano Mansillagodoy",
            "autor_image": "https://lh3.googleusercontent.com/a/ACg8ocLr06RTYWa4UsCrePDyIewzQ1Bt_FoIZRIEHpayArykAOO5Tg=s120-c-rp-mo-br100",
            "review_text": "Hermoso lugar. Un pedacito de cielo",
            "review_link": "https://www.google.com/maps/reviews/data=!4m8!14m7!1m6!2m5!1sCi9DQUlRQUNvZENodHljRjlvT2pkV1VYSmFXbnBKY1V4dWRrWklWbU5GVGtsTFZrRRAB!2m1!1s0x0:0xe7f57694b5338ff2!3m1!1s2@1:CAIQACodChtycF9oOjdWUXJaWnpJcUxudkZIVmNFTklLVkE%7C0dIK4puvqg5%7C?hl=en",
            "review_rating": "5",
            "review_date": "25/12/2025"
        },
        {
            "autor_name": "Nicolas Schvartzman",
            "autor_image": "https://lh3.googleusercontent.com/a/ACg8ocKZIK08ZG2bUbvtrFYsvdgkf1PwZ7ItDKFzF7kJN_ex8WmFuQ=s120-c-rp-mo-br100",
            "review_text": "Excelentes instalaciones y muy buena atenci칩n. Buena ubicaci칩n, a pocas cuadras de la zona comercial. Muy recomendable",
            "review_link": "https://www.google.com/maps/reviews/data=!4m8!14m7!1m6!2m5!1sCi9DQUlRQUNvZENodHljRjlvT2xWcmVFUmpiR3ROTlRORGEwUlVUa1ZGV2xFdFIyYxAB!2m1!1s0x0:0xe7f57694b5338ff2!3m1!1s2@1:CAIQACodChtycF9oOlVreERjbGtNNTNDa0RUTkVFWlEtR2c%7C0dHe_6dB0T5%7C?hl=en",
            "review_rating": "5",
            "review_date": "23/12/2025"
        },
        {
            "autor_name": "Irma Elisa Gonzalez",
            "autor_image": "https://lh3.googleusercontent.com/a-/ALV-UjWS6q__5zTvUeQLY_JkEwqp5KJAxJouVNqMAV7lCohzG63Os4Hprg=s120-c-rp-mo-br100",
            "review_text": "Maravilloso lugar. Excelente atenci칩n. Rodeado de naturaleza y paz. Un recomendado lugar para descansar.",
            "review_link": "https://www.google.com/maps/reviews/data=!4m8!14m7!1m6!2m5!1sCi9DQUlRQUNvZENodHljRjlvT2xWMmMweE1RMUpvUkZoMVozRndkVEZ1VTNWcFJXYxAB!2m1!1s0x0:0xe7f57694b5338ff2!3m1!1s2@1:CAIQACodChtycF9oOlV2c0xMQ1JoRFh1Z3FwdTFuU3VpRWc%7C0dGT2C7nr4U%7C?hl=en",
            "review_rating": "5",
            "review_date": "19/12/2025"
        },
        {
            "autor_name": "Juan Carlos Irigoyen",
            "autor_image": "https://lh3.googleusercontent.com/a-/ALV-UjUFLIujBfSbxBhud8X6_hIdYJnp7Kd3KprDyk9JMtQlDwDXAVBJAw=s120-c-rp-mo-br100",
            "review_text": "Hermoso lugar.muy buena atenci칩n muy lindas caba침as",
            "review_link": "https://www.google.com/maps/reviews/data=!4m8!14m7!1m6!2m5!1sCi9DQUlRQUNvZENodHljRjlvT2paVFpGQkJTVEJoYWpNNU1IVjBUVzV1Ukd4Tk4xRRAB!2m1!1s0x0:0xe7f57694b5338ff2!3m1!1s2@1:CAIQACodChtycF9oOjZTZFBBSTBhajM5MHV0TW5uRGxNN1E%7C0dGSoClJnvg%7C?hl=en",
            "review_rating": "5",
            "review_date": "19/12/2025"
        },
        {
            "autor_name": "ENRIQUE ALDO VIEGAS DA LUZ",
            "autor_image": "https://lh3.googleusercontent.com/a-/ALV-UjXedIrUBtz2PkbDjEZIBQKGZgBZfSOsp9k7JjjJm8ScTxGnO2Qy4w=s120-c-rp-mo-ba3-br100",
            "review_text": "Excelente lugar para descansar. La caba침a est치 impecablemente limpia, con ba침o en muy buen estado, agua caliente y buen internet. El entorno es muy tranquilo y a la vez est치 cerca de todo: supermercados, estaciones de servicio y los principales puntos para visitar. La atenci칩n del due침o es excelente, siempre atento y amable. Muy recomendable.",
            "review_link": "https://www.google.com/maps/reviews/data=!4m8!14m7!1m6!2m5!1sCi9DQUlRQUNvZENodHljRjlvT2tWdFduaFFPRFEwYTJKT05GWTRXbkZZTFZVdFoxRRAB!2m1!1s0x0:0xe7f57694b5338ff2!3m1!1s2@1:CAIQACodChtycF9oOkVtWnhQODQ0a2JONFY4WnFYLVUtZ1E%7C0dGRKT5SMiE%7C?hl=en",
            "review_rating": "5",
            "review_date": "19/12/2025"
        },
        {
            "autor_name": "Natalia Iaria",
            "autor_image": "https://lh3.googleusercontent.com/a-/ALV-UjXOaHHx_yYB_4c4wBirDwWDFPySmlduJfHe5mUqp6IRZDdPfQP8cw=s120-c-rp-mo-ba4-br100",
            "review_text": "La caba침a es hermosa y con una decoraci칩n que la hace absolutamente c치lida. La ubicaci칩n es muy buena, ya que est치 muy cerca del centro por lo que se puede ir caminando a cualquier comercio y tienen muy cerca la parada del colectivo que te acerca a los lugares m치s tur칤sticos. Menci칩n aparte para Silvia y Gustavo, los due침os, dos personas completamente amables y siempre dispuestos a ayudar. Si est치n buscando un lugar donde hospedarse para pasar unos bellos d칤as, no lo duden.",
            "review_link": "https://www.google.com/maps/reviews/data=!4m8!14m7!1m6!2m5!1sCi9DQUlRQUNvZENodHljRjlvT2w4MlVsQTVWbUpwU2tKNk0xaFpRbUowZGt4Q1owRRAB!2m1!1s0x0:0xe7f57694b5338ff2!3m1!1s2@1:CAIQACodChtycF9oOl82UlA5VmJpSkJ6M1hZQmJ0dkxCZ0E%7C0caSUpk9DaC%7C?hl=en",
            "review_rating": "5",
            "review_date": "11/08/2025"
        },
        {
            "autor_name": "Marcos Lhomy",
            "autor_image": "https://lh3.googleusercontent.com/a-/ALV-UjW6Mvu-knz7lSm2NY_sOghs-g5P1RZMRg0oY7i4Lmi6I0S_ICZw5g=s120-c-rp-mo-ba4-br100",
            "review_text": "Excelente caba침a, c치lida, muy bien ubicada a 300mts del centro de Lago Puelo y a 5 minutos en auto del parque nacional. Tiene todas las comodidades, super cuidado y cuenta con un jardin para tomar mates al sol. Silvia la due침a es super amorosa y atenta, nos ayudo con todo lo que necesitamos. Aceptan mascotas! Muy recomendable!!",
            "review_link": "https://www.google.com/maps/reviews/data=!4m8!14m7!1m6!2m5!1sChZDSUhNMG9nS0VJQ0FnTUNJdThpNVNBEAE!2m1!1s0x0:0xe7f57694b5338ff2!3m1!1s2@1:CIHM0ogKEICAgMCIu8i5SA%7CCgwI1c7BvwYQ2L2FwAE%7C?hl=en",
            "review_rating": "5",
            "review_date": "04/04/2025"
        },
        {
            "autor_name": "Fabricio Colo",
            "autor_image": "https://lh3.googleusercontent.com/a-/ALV-UjUJYq4Q4HRNHm9V3LI2i7wT68dTmNln69WNFjMZ8G6HmyS8AGp_yw=s120-c-rp-mo-ba3-br100",
            "review_text": "Muy buen lugar para venir a pasar tranquilo unas lindas vacaciones cerca de la monta침a y para los amantes de la naturaleza 游륊잺\nLago Puelo tiene gran variedad de senderos para hacer Hiking y Trekking",
            "review_link": "https://www.google.com/maps/reviews/data=!4m8!14m7!1m6!2m5!1sChdDSUhNMG9nS0VJQ0FnSURmc2VQbnBBRRAB!2m1!1s0x0:0xe7f57694b5338ff2!3m1!1s2@1:CIHM0ogKEICAgIDfsePnpAE%7CCgwIoaL1uwYQoJW6xgM%7C?hl=en",
            "review_rating": "5",
            "review_date": "07/01/2025"
        },
        {
            "autor_name": "claudia prieto",
            "autor_image": "https://lh3.googleusercontent.com/a-/ALV-UjXsXj7-AfjQrg-QwiZXkff4qceo3Ue7nVO1aFy1E4ytBNFxz0X4Cg=s120-c-rp-mo-ba3-br100",
            "review_text": "Relacion precio calidad, excelente.\nGustavo es muy atento y Silvia hace unos dulces caseros muy ricos.",
            "review_link": "https://www.google.com/maps/reviews/data=!4m8!14m7!1m6!2m5!1sChZDSUhNMG9nS0VJQ0FnSURmeEtEOUVBEAE!2m1!1s0x0:0xe7f57694b5338ff2!3m1!1s2@1:CIHM0ogKEICAgIDfxKD9EA%7CCgwI0-zhuwYQ4PKnuwM%7C?hl=en",
            "review_rating": "5",
            "review_date": "03/01/2025"
        },
        {
            "autor_name": "Karina Sacks",
            "autor_image": "https://lh3.googleusercontent.com/a-/ALV-UjUOeM4E8xUIPwV_K7XbrjY0nvuX8AP1Zi1xKzONFpuK6YNTncKzFw=s120-c-rp-mo-ba4-br100",
            "review_text": null,
            "review_link": "https://www.google.com/maps/reviews/data=!4m8!14m7!1m6!2m5!1sChZDSUhNMG9nS0VJQ0FnSURIdGU2dlJ3EAE!2m1!1s0x0:0xe7f57694b5338ff2!3m1!1s2@1:CIHM0ogKEICAgIDHte6vRw%7CCgwIuvCrtwYQgMa4ogM%7C?hl=en",
            "review_rating": "5",
            "review_date": "18/09/2024"
        },
        {
            "autor_name": "Lauu Kleber",
            "autor_image": "https://lh3.googleusercontent.com/a/ACg8ocIz67zOmNjpFZvpvzaDijcF4nlzsw88fHxPh0D7W1eTwiiNqn4=s120-c-rp-mo-br100",
            "review_text": "Hermoso y muy tranquilo, con todo lo necesario para tener una estadia c칩moda y dentro de todo, economica. La ubicaci칩n es genial, sobre todo si andan sin veh칤culo porque est치 muy cerca de los locales y del centro. La atenci칩n del due침o muy buena, siempre dispuesto a ayudar, nos fuimos muy contentos y con ganas de volver alg칰n d칤a, ojal치.  Gracias 游똂",
            "review_link": "https://www.google.com/maps/reviews/data=!4m8!14m7!1m6!2m5!1sChZDSUhNMG9nS0VJQ0FnSURqb3VTN1N3EAE!2m1!1s0x0:0xe7f57694b5338ff2!3m1!1s2@1:CIHM0ogKEICAgIDjouS7Sw%7CCgwInMXGsQYQkJm53wE%7C?hl=en",
            "review_rating": "5",
            "review_date": "01/05/2024"
        },
        {
            "autor_name": "Juan Manuel Vallejo",
            "autor_image": "https://lh3.googleusercontent.com/a/ACg8ocKMM29qbsxOFp84-kjq8KOwEQvdDiy_Zpj8_E-kLPGWfOuvZw=s120-c-rp-mo-ba3-br100",
            "review_text": "Bonita y sencilla caba침a para 4 personas (habitaci칩n con cama doble y 2 camas simples en el estar), al borde de la zona urbana principal de Lago Puelo, y a s칩lo 4km de la costa del lago. El due침o super amable y atento.",
            "review_link": "https://www.google.com/maps/reviews/data=!4m8!14m7!1m6!2m5!1sChdDSUhNMG9nS0VJQ0FnSUNqdWZyUnJBRRAB!2m1!1s0x0:0xe7f57694b5338ff2!3m1!1s2@1:CIHM0ogKEICAgICjufrRrAE%7CCgsI0sifsQYQwOeudw%7C?hl=en",
            "review_rating": "4",
            "review_date": "23/04/2024"
        },
        {
            "autor_name": "Romina Gonzalez",
            "autor_image": "https://lh3.googleusercontent.com/a-/ALV-UjVfn84eAw0cr52AHHW_wVOMCdTbEHvCY_G8erfcDvhdyUxAHebZ=s120-c-rp-mo-ba3-br100",
            "review_text": "Una caba침a muy tranquila y equipada. Pasamos una noche en familia hermosa con mucha paz. Hab칤a un gatito muy simpatico que nos encanto. Gustavo un genio!",
            "review_link": "https://www.google.com/maps/reviews/data=!4m8!14m7!1m6!2m5!1sChdDSUhNMG9nS0VJQ0FnSUNEbjlqenJnRRAB!2m1!1s0x0:0xe7f57694b5338ff2!3m1!1s2@1:CIHM0ogKEICAgICDn9jzrgE%7CCgsIxJi2sAYQ6PajZQ%7C?hl=en",
            "review_rating": "5",
            "review_date": "03/04/2024"
        },
        {
            "autor_name": "Martin Moyano",
            "autor_image": "https://lh3.googleusercontent.com/a/ACg8ocJvstXM3Ax1ghTtFnnCXielO-jv8gza01BT90720yt30PvN8A=s120-c-rp-mo-ba3-br100",
            "review_text": "Simplemente perfecto en todo sentido... Apostamos 10 d칤as ah칤 y fue la mejor decisi칩n.... Tanto yo como m칤 familia quedamos conforme... Hab칤a un gato que abr칤a la puerta muy lindo... Lo tuvimos que mimar ojal치 todos lo hagan.\nTodo lo necesario para pasar una grata estad칤a...",
            "review_link": "https://www.google.com/maps/reviews/data=!4m8!14m7!1m6!2m5!1sChZDSUhNMG9nS0VJQ0FnSUM5OGFqakVBEAE!2m1!1s0x0:0xe7f57694b5338ff2!3m1!1s2@1:CIHM0ogKEICAgIC98ajjEA%7CCgwIzOSirwYQwO2ChQE%7C?hl=en",
            "review_rating": "5",
            "review_date": "06/03/2024"
        },
        {
            "autor_name": "amalia wohn",
            "autor_image": "https://lh3.googleusercontent.com/a-/ALV-UjUXwNRBOV8XPrl-ctY-TjfxGG5-OGi60m_WBhfmw-0gDbBnxYjn=s120-c-rp-mo-br100",
            "review_text": null,
            "review_link": "https://www.google.com/maps/reviews/data=!4m8!14m7!1m6!2m5!1sChZDSUhNMG9nS0VJQ0FnSURkbTlQTmNREAE!2m1!1s0x0:0xe7f57694b5338ff2!3m1!1s2@1:CIHM0ogKEICAgIDdm9PNcQ%7CCgwIhMv3rgYQsI7aqQM%7C?hl=en",
            "review_rating": "5",
            "review_date": "27/02/2024"
        },
        {
            "autor_name": "Mago Abdo",
            "autor_image": "https://lh3.googleusercontent.com/a-/ALV-UjXF32aTjT3o2Ao9mdQh0R_v7DFT2ZGE_ZVjhEFK3o2mKVKNYM0=s120-c-rp-mo-ba3-br100",
            "review_text": null,
            "review_link": "https://www.google.com/maps/reviews/data=!4m8!14m7!1m6!2m5!1sChdDSUhNMG9nS0VJQ0FnSURkMk9ERGhRRRAB!2m1!1s0x0:0xe7f57694b5338ff2!3m1!1s2@1:CIHM0ogKEICAgIDd2ODDhQE%7CCgsI74_UrgYQsLe6Rg%7C?hl=en",
            "review_rating": "5",
            "review_date": "20/02/2024"
        },
        {
            "autor_name": "Daniela G칩mez",
            "autor_image": "https://lh3.googleusercontent.com/a-/ALV-UjU1x5V3beL_jXdL281J9dfV6Nb1yURNk6_9MszwMTBqLrae4paC=s120-c-rp-mo-ba2-br100",
            "review_text": "Buena",
            "review_link": "https://www.google.com/maps/reviews/data=!4m8!14m7!1m6!2m5!1sChdDSUhNMG9nS0VJQ0FnSUNkbXZ6NWhnRRAB!2m1!1s0x0:0xe7f57694b5338ff2!3m1!1s2@1:CIHM0ogKEICAgICdmvz5hgE%7CCgwIgpezrgYQsN_ixwM%7C?hl=en",
            "review_rating": "4",
            "review_date": "14/02/2024"
        },
        {
            "autor_name": "Daniel Albornoz",
            "autor_image": "https://lh3.googleusercontent.com/a-/ALV-UjU-ZSzgjP3aJ72mxUkGye-NDNn6e7qM_KoS4BfmHVAi4t8y9l4ekA=s120-c-rp-mo-ba4-br100",
            "review_text": null,
            "review_link": "https://www.google.com/maps/reviews/data=!4m8!14m7!1m6!2m5!1sChdDSUhNMG9nS0VJQ0FnSUNkN0k2eHFnRRAB!2m1!1s0x0:0xe7f57694b5338ff2!3m1!1s2@1:CIHM0ogKEICAgICd7I6xqgE%7CCgwI3O6trgYQ-KS99gI%7C?hl=en",
            "review_rating": "3",
            "review_date": "13/02/2024"
        },
        {
            "autor_name": "Flavio Tapia",
            "autor_image": "https://lh3.googleusercontent.com/a-/ALV-UjUuFR8dDi8dnbKDi168i2OGCYk6wPsaj0rSz_3Dabytnsnolwj9=s120-c-rp-mo-ba5-br100",
            "review_text": "La Caba침a  para 4 personas, sencilla. Con ventilador en living y habitaci칩n. Todos los elementos de cocina. Parrilla y mesa en el. Exterior Cercano al centro y a la ruta al lago. Excelente relaci칩n calidad precio. Muy amable Gustavo.",
            "review_link": "https://www.google.com/maps/reviews/data=!4m8!14m7!1m6!2m5!1sChZDSUhNMG9nS0VJQ0FnSURON2VlUFNREAE!2m1!1s0x0:0xe7f57694b5338ff2!3m1!1s2@1:CIHM0ogKEICAgIDN7eePSQ%7CCgwIo5L6rQYQ2NibjAE%7C?hl=en",
            "review_rating": "4",
            "review_date": "03/02/2024"
        },
        {
            "autor_name": "Martin Aguirrezarobe",
            "autor_image": "https://lh3.googleusercontent.com/a/ACg8ocKa5KlfqmpottihGqV33Cjs3Q7nA8HK_kiHxwsAXZXhf4GQEA=s120-c-rp-mo-br100",
            "review_text": null,
            "review_link": "https://www.google.com/maps/reviews/data=!4m8!14m7!1m6!2m5!1sChdDSUhNMG9nS0VJQ0FnSUR0aks3VHpRRRAB!2m1!1s0x0:0xe7f57694b5338ff2!3m1!1s2@1:CIHM0ogKEICAgIDtjK7TzQE%7CCgsI-NH1rQYQ-Mftdg%7C?hl=en",
            "review_rating": "5",
            "review_date": "02/02/2024"
        },
        {
            "autor_name": "Victor Risso",
            "autor_image": "https://lh3.googleusercontent.com/a/ACg8ocJREaaCe1X-xI9J20mF7QRNTtu8ks8Y_bOcghxp0ejpNPnucg=s120-c-rp-mo-br100",
            "review_text": "Excelente lugar, muy limpio, todas las comodidades, tranquilo, cerca del centro, el due침o muy atento. Seguramente volveremos. Recomendable 100%",
            "review_link": "https://www.google.com/maps/reviews/data=!4m8!14m7!1m6!2m5!1sChZDSUhNMG9nS0VJQ0FnSURONTdDWU1REAE!2m1!1s0x0:0xe7f57694b5338ff2!3m1!1s2@1:CIHM0ogKEICAgIDN57CYMQ%7CCgsIuJ7QrQYQ4NLXfQ%7C?hl=en",
            "review_rating": "5",
            "review_date": "26/01/2024"
        },
        {
            "autor_name": "Laila Abbas",
            "autor_image": "https://lh3.googleusercontent.com/a/ACg8ocJqPw9vlB4hy5ym78ZcZS8ESE7DGPwvRtKl9kWpjwrUsmTXy7Of=s120-c-rp-mo-ba3-br100",
            "review_text": "Excelente atenci칩n, una caba침a amplia con todas las comodidades. Muy recomendable",
            "review_link": "https://www.google.com/maps/reviews/data=!4m8!14m7!1m6!2m5!1sChdDSUhNMG9nS0VJQ0FnSUNsMHN6a3dBRRAB!2m1!1s0x0:0xe7f57694b5338ff2!3m1!1s2@1:CIHM0ogKEICAgICl0szkwAE%7CCgsIqLnRqgYQiJrRHg%7C?hl=en",
            "review_rating": "5",
            "review_date": "15/11/2023"
        },
        {
            "autor_name": "#",
            "autor_image": "https://lh3.googleusercontent.com/a/ACg8ocLii5aBtwtP22aZ-_OtYeiynjpwv2pRgkvGwlsB6a-QR7xm9g=s120-c-rp-mo-ba3-br100",
            "review_text": null,
            "review_link": "https://www.google.com/maps/reviews/data=!4m8!14m7!1m6!2m5!1sChZDSUhNMG9nS0VJQ0FnSUNsMk9PYll3EAE!2m1!1s0x0:0xe7f57694b5338ff2!3m1!1s2@1:CIHM0ogKEICAgICl2OObYw%7CCgwItL7KqgYQuOGg9QE%7C?hl=en",
            "review_rating": "5",
            "review_date": "13/11/2023"
        },
        {
            "autor_name": "Belen Sarratea",
            "autor_image": "https://lh3.googleusercontent.com/a/ACg8ocLKJDZMOTTiaDixX2v5YIKmPHQik7gFo4cx6ROoH6mJfxn1ZA=s120-c-rp-mo-ba3-br100",
            "review_text": "La caba침a es muy linda, esta todo limpio. Es un lindo lugar para descansar. Esta cerca del centro, si van caminando es un poco oscuro de noche pero se llega rapido. El colectivo que llega al Lago tambien pasa cerca.",
            "review_link": "https://www.google.com/maps/reviews/data=!4m8!14m7!1m6!2m5!1sChZDSUhNMG9nS0VJQ0FnSURoMnI2bWZBEAE!2m1!1s0x0:0xe7f57694b5338ff2!3m1!1s2@1:CIHM0ogKEICAgIDh2r6mfA%7CCgsIppCZoAYQ6JbuLQ%7C?hl=en",
            "review_rating": "4",
            "review_date": "06/03/2023"
        },
        {
            "autor_name": "emanuel s",
            "autor_image": "https://lh3.googleusercontent.com/a/ACg8ocLWAAX-7AM3H7sG_G-k4kWohf7igf0pcIIIJNJUOw_uRe34xg=s120-c-rp-mo-ba3-br100",
            "review_text": "Impecable la limpieza, la tranquilidad del lugar, dormis muuuy bien! La atencion del due침o de 10, nos dieron toallon, jabon,shampoo! Nos cobraron $7000 febrero 2022! Me encanto",
            "review_link": "https://www.google.com/maps/reviews/data=!4m8!14m7!1m6!2m5!1sChZDSUhNMG9nS0VJQ0FnSUNXa3RXd1BnEAE!2m1!1s0x0:0xe7f57694b5338ff2!3m1!1s2@1:CIHM0ogKEICAgICWktWwPg%7CCgwIyaTTkAYQyIqDlAE%7C?hl=en",
            "review_rating": "5",
            "review_date": "22/02/2022"
        },
        {
            "autor_name": "818lul_g",
            "autor_image": "https://lh3.googleusercontent.com/local-reviews/AJMZ0QeWB0GIG9gGd6g9zDFXwjE9TRuKRtAO6HvwA5jEdK_CrOJXcVxp8esjQRYTFMjay2JK=s120-c-br100",
            "review_text": "Las caba침as est치 s칰per bien ubicadas, a tres cuadras del centro pero en una zona muy tranquila. El jard칤n es hermoso para pasar un rato de descanso y tranquilidad.||Los due침os son super atentos y mantienen todo m치s que impecable, pasamos unos d칤as hermosos. Gracias!",
            "review_link": "https://www.tripadvisor.es/ShowUserReviews-g3205091-d16877803-r782525666?m=68573&staydates=2026_02_15_2026_02_16&uguests=1_2_0&supdv=desktop&supuc=US&supul=en",
            "review_rating": "5",
            "review_date": "08/02/2021"
        },
        {
            "autor_name": "Florencia Souza Rey",
            "autor_image": "https://lh3.googleusercontent.com/a-/ALV-UjUmJlkfAqnYjS04jYb5juVz2h_IFZCS-793iqFaWfiA-t5DRP5n=s120-c-rp-mo-ba2-br100",
            "review_text": "Excelente lugar para descansar. La caba침a es super acogedora y el due침o muy amable. Nos acepto con nuestra mascota de manera gentil. Lo recomendamos!",
            "review_link": "https://www.google.com/maps/reviews/data=!4m8!14m7!1m6!2m5!1sChdDSUhNMG9nS0VJQ0FnSURTei1XbTRnRRAB!2m1!1s0x0:0xe7f57694b5338ff2!3m1!1s2@1:CIHM0ogKEICAgIDSz-Wm4gE%7CCgsIroD8_wUQyOOxXw%7C?hl=en",
            "review_rating": "5",
            "review_date": "13/01/2021"
        },
        {
            "autor_name": "Federico Brunfman",
            "autor_image": "https://lh3.googleusercontent.com/a-/ALV-UjWAt6DMAtHySKahLmWYa0hq4vi_vy_kyZsSrdzBBEhZ41zuhxhEvA=s120-c-rp-mo-br100",
            "review_text": null,
            "review_link": "https://www.google.com/maps/reviews/data=!4m8!14m7!1m6!2m5!1sChZDSUhNMG9nS0VJQ0FnSURTLVlTU1lBEAE!2m1!1s0x0:0xe7f57694b5338ff2!3m1!1s2@1:CIHM0ogKEICAgIDS-YSSYA%7CCgwIk6u9_wUQ-NjbhQI%7C?hl=en",
            "review_rating": "5",
            "review_date": "01/01/2021"
        },
        {
            "autor_name": "MrAle09",
            "autor_image": "https://lh3.googleusercontent.com/a-/ALV-UjWhAONFAE4uYrrGgLTjA-ZbrMnsMGc3xaamT8lGTDwpMV-W9TatkQ=s120-c-rp-mo-ba3-br100",
            "review_text": null,
            "review_link": "https://www.google.com/maps/reviews/data=!4m8!14m7!1m6!2m5!1sChZDSUhNMG9nS0VJQ0FnSUNTMHNhWElBEAE!2m1!1s0x0:0xe7f57694b5338ff2!3m1!1s2@1:CIHM0ogKEICAgICS0saXIA%7CCgwIt5Hl_gUQiOjYkAE%7C?hl=en",
            "review_rating": "3",
            "review_date": "15/12/2020"
        },
        {
            "autor_name": "Nicolas Garcia",
            "autor_image": "https://lh3.googleusercontent.com/a-/ALV-UjUf7YDaF5fDbXzoNJd-ZI9Jm_hnEmJ0apLoIOpo9qKP7pteo5IzqA=s120-c-rp-mo-ba5-br100",
            "review_text": "Excelente , buena atenci칩n del propietario, las caba침as muy acogedoras. Precio acorde.",
            "review_link": "https://www.google.com/maps/reviews/data=!4m8!14m7!1m6!2m5!1sChZDSUhNMG9nS0VJQ0FnSUNjaHVpa1RREAE!2m1!1s0x0:0xe7f57694b5338ff2!3m1!1s2@1:CIHM0ogKEICAgICchuikTQ%7CCgwIysS78wUQ8Py5iAI%7C?hl=en",
            "review_rating": "5",
            "review_date": "16/03/2020"
        },
        {
            "autor_name": "Iv치n Palmero",
            "autor_image": "https://lh3.googleusercontent.com/a/ACg8ocLEPMGZbyhapt6VxBNxsvcbbBmh1u_ek0JcRXS8eZXh5AIPFIaB=s120-c-rp-mo-ba5-br100",
            "review_text": null,
            "review_link": "https://www.google.com/maps/reviews/data=!4m8!14m7!1m6!2m5!1sChZDSUhNMG9nS0VJQ0FnSURzLXNxamNnEAE!2m1!1s0x0:0xe7f57694b5338ff2!3m1!1s2@1:CIHM0ogKEICAgIDs-sqjcg%7CCgsIlo3x8gUQ4Ly0HA%7C?hl=en",
            "review_rating": "4",
            "review_date": "01/03/2020"
        },
        {
            "autor_name": "Walter Ariel Doria",
            "autor_image": "https://lh3.googleusercontent.com/a-/ALV-UjU92RxHUAhRTmPyFQJW3Ik1veNMJH8J1TXdZouotQA8ECUCCf-T=s120-c-rp-mo-ba4-br100",
            "review_text": "Hermoso lugar",
            "review_link": "https://www.google.com/maps/reviews/data=!4m8!14m7!1m6!2m5!1sChZDSUhNMG9nS0VJQ0FnSURzb3RMR0pREAE!2m1!1s0x0:0xe7f57694b5338ff2!3m1!1s2@1:CIHM0ogKEICAgIDsotLGJQ%7CCgwIvOfg8gUQ-K_XgAE%7C?hl=en",
            "review_rating": "5",
            "review_date": "27/02/2020"
        },
        {
            "autor_name": "Martin Gauna",
            "autor_image": "https://lh3.googleusercontent.com/a/ACg8ocIJEzXlQHA5pKNiMX3t2fbB7jst4Aj_-1BVQaqeX0FFKC6keg=s120-c-rp-mo-br100",
            "review_text": "Es una casa muy tranquila y los due침os son muy macanudos",
            "review_link": "https://www.google.com/maps/reviews/data=!4m8!14m7!1m6!2m5!1sChdDSUhNMG9nS0VJQ0FnSUNzaWJDTnB3RRAB!2m1!1s0x0:0xe7f57694b5338ff2!3m1!1s2@1:CIHM0ogKEICAgICsibCNpwE%7CCgwIsuq-8gUQyL2wowM%7C?hl=en",
            "review_rating": "4",
            "review_date": "21/02/2020"
        },
        {
            "autor_name": "Cristian Gonzalez",
            "autor_image": "https://lh3.googleusercontent.com/a/ACg8ocK1T_vvP-q47dD3ES2vjqVdEWNQDnznyheHIwqkPhu3jeHSMQ=s120-c-rp-mo-br100",
            "review_text": null,
            "review_link": "https://www.google.com/maps/reviews/data=!4m8!14m7!1m6!2m5!1sChZDSUhNMG9nS0VJQ0FnSUNzODdHYmVBEAE!2m1!1s0x0:0xe7f57694b5338ff2!3m1!1s2@1:CIHM0ogKEICAgICs87GbeA%7CCgwI8uWX8gUQ4OSjtgE%7C?hl=en",
            "review_rating": "5",
            "review_date": "14/02/2020"
        },
        {
            "autor_name": "Roberto Alaniz",
            "autor_image": "https://lh3.googleusercontent.com/a-/ALV-UjUy457__G4nIvS-dTR8eStY6OlMzzTM2KoAtvvWO-0Uuae-SWdH=s120-c-rp-mo-ba4-br100",
            "review_text": "Sencillo y lindo",
            "review_link": "https://www.google.com/maps/reviews/data=!4m8!14m7!1m6!2m5!1sChZDSUhNMG9nS0VJQ0FnSUNzcFl6N2Z3EAE!2m1!1s0x0:0xe7f57694b5338ff2!3m1!1s2@1:CIHM0ogKEICAgICspYz7fw%7CCgsIxvL78QUQgO-2NQ%7C?hl=en",
            "review_rating": "3",
            "review_date": "08/02/2020"
        },
        {
            "autor_name": "Alejandra Vittola",
            "autor_image": "https://lh3.googleusercontent.com/a-/ALV-UjUfVoQdk2P831aNSsOM8DhODyzrZLJe_-yi75omXuReP9lQrtIghA=s120-c-rp-mo-ba3-br100",
            "review_text": null,
            "review_link": "https://www.google.com/maps/reviews/data=!4m8!14m7!1m6!2m5!1sChdDSUhNMG9nS0VJQ0FnSUNzMmJDTl93RRAB!2m1!1s0x0:0xe7f57694b5338ff2!3m1!1s2@1:CIHM0ogKEICAgICs2bCN_wE%7CCgwI9L318QUQ0OaRuwM%7C?hl=en",
            "review_rating": "4",
            "review_date": "07/02/2020"
        },
        {
            "autor_name": "Marita Guzman",
            "autor_image": "https://lh3.googleusercontent.com/a-/ALV-UjVweizogQBvRjEMw6qqDdBUiK0jSjq73pJaWnSkYoRLXDSZi_w=s120-c-rp-mo-br100",
            "review_text": null,
            "review_link": "https://www.google.com/maps/reviews/data=!4m8!14m7!1m6!2m5!1sChdDSUhNMG9nS0VJQ0FnSUNzbEphd3hRRRAB!2m1!1s0x0:0xe7f57694b5338ff2!3m1!1s2@1:CIHM0ogKEICAgICslJawxQE%7CCgwIwpmk8QUQiMvp0wE%7C?hl=en",
            "review_rating": "5",
            "review_date": "23/01/2020"
        },
        {
            "autor_name": "pablo arribillaga",
            "autor_image": "https://lh3.googleusercontent.com/a-/ALV-UjUzSJ1B8qBHeMIRH_6XEqzmZz-KNW0YSE3ejpHJbfL3nHKkedMVoQ=s120-c-rp-mo-ba2-br100",
            "review_text": "Buena atenci칩n y servicio",
            "review_link": "https://www.google.com/maps/reviews/data=!4m8!14m7!1m6!2m5!1sChZDSUhNMG9nS0VJQ0FnSUNzaUlPcWN3EAE!2m1!1s0x0:0xe7f57694b5338ff2!3m1!1s2@1:CIHM0ogKEICAgICsiIOqcw%7CCgwIwZSU8QUQiMbiwgM%7C?hl=en",
            "review_rating": "4",
            "review_date": "20/01/2020"
        },
        {
            "autor_name": "Hern치n Luna",
            "autor_image": "https://lh3.googleusercontent.com/a-/ALV-UjUZXc5YwRRDhIlffM3cMVhqh_9d_MIEgRA-vFWnvRN8avyOpIk=s120-c-rp-mo-br100",
            "review_text": "Totalmente completas, muy buena ubicaci칩n, c칩modas, zona muy  tranquila...sombra par el auto y sobre todas las cosas tiene todo para hacer asado...exelente lugar",
            "review_link": "https://www.google.com/maps/reviews/data=!4m8!14m7!1m6!2m5!1sChZDSUhNMG9nS0VJQ0FnSURNbWZmbWJnEAE!2m1!1s0x0:0xe7f57694b5338ff2!3m1!1s2@1:CIHM0ogKEICAgIDMmffmbg%7CCgwIqJPD8AUQ6LnaiwM%7C?hl=en",
            "review_rating": "5",
            "review_date": "04/01/2020"
        },
        {
            "autor_name": "Leonardo Rodriguez Pietroroia",
            "autor_image": "https://lh3.googleusercontent.com/a-/ALV-UjXaPNXnhsswhAbSpBU0okkJWYvB9lEiB8mWwnvJWcSsgzdwzyDJJQ=s120-c-rp-mo-ba4-br100",
            "review_text": null,
            "review_link": "https://www.google.com/maps/reviews/data=!4m8!14m7!1m6!2m5!1sChdDSUhNMG9nS0VJQ0FnSURNc2JqMXhBRRAB!2m1!1s0x0:0xe7f57694b5338ff2!3m1!1s2@1:CIHM0ogKEICAgIDMsbj1xAE%7CCgsIwKq58AUQqPX7Mw%7C?hl=en",
            "review_rating": "5",
            "review_date": "02/01/2020"
        },
        {
            "autor_name": "lidia beatriz toscana",
            "autor_image": "https://lh3.googleusercontent.com/a-/ALV-UjVIZZyBtLd_f4nUPEqFfN2kusxGGYLo9HRKxTiOJazXNEsbeSaH=s120-c-rp-mo-br100",
            "review_text": "Excelente lugar para disfrutar. La caba침a comoda agradable. La ropa de cama y el colch칩n adecuados para descansar.  Los anfitriones amables y atentos a todo lo que se necesite.",
            "review_link": "https://www.google.com/maps/reviews/data=!4m8!14m7!1m6!2m5!1sChZDSUhNMG9nS0VJQ0FnSURNbHBDaWN3EAE!2m1!1s0x0:0xe7f57694b5338ff2!3m1!1s2@1:CIHM0ogKEICAgIDMlpCicw%7CCgsIgbuf8AUQyNqVFg%7C?hl=en",
            "review_rating": "5",
            "review_date": "28/12/2019"
        },
        {
            "autor_name": "Francisco Ordoqui",
            "autor_image": "https://lh3.googleusercontent.com/a/ACg8ocJ6lVmhcudO53_wkL_-kBbYmUz3DoHHcTtjv7D8BOOrJH_zWw=s120-c-rp-mo-br100",
            "review_text": null,
            "review_link": "https://www.google.com/maps/reviews/data=!4m8!14m7!1m6!2m5!1sChZDSUhNMG9nS0VJQ0FnSUNNbGIzaExnEAE!2m1!1s0x0:0xe7f57694b5338ff2!3m1!1s2@1:CIHM0ogKEICAgICMlb3hLg%7CCgwI8ZyB7wUQgPvQogM%7C?hl=en",
            "review_rating": "5",
            "review_date": "28/11/2019"
        },
        {
            "autor_name": "tavos192",
            "autor_image": "https://lh3.googleusercontent.com/local-reviews/AJMZ0QeqQESQs2CRf2VRyln1Raq0k2FSdB19mGKme5Xh6nHXcs2V7pTrOayJAdxC-qWdu9VyTA=s120-c-br100",
            "review_text": "Ubicadas a pasos del centro comercial de Lago Puelo a s칩lo 3km del Parque Nacional Lago Puelo donde se puede disfrutar de d칤as de playa, senderos interpretativos, caminatas en medio del bosque, kayaks, paseos en el lago etc...|A disfrutar!!!",
            "review_link": "https://www.tripadvisor.es/ShowUserReviews-g3205091-d16877803-r723774608?m=68573&staydates=2026_02_15_2026_02_16&uguests=1_2_0&supdv=desktop&supuc=US&supul=en",
            "review_rating": "5",
            "review_date": "04/11/2019"
        },
        {
            "autor_name": "silvinanoelia1981",
            "autor_image": "https://lh3.googleusercontent.com/local-reviews/AJMZ0QeSe9ibNVY65MpgeQh70I370foM0-7tEPyVc9CIfSq5Ekli093sZJVPBoLD5d5qPK_2rw=s120-c-br100",
            "review_text": "La ubicaci칩n es excelente, est치s en pleno centro de Lago Puelo con dos super cerca, farmacia, rotiser칤a, y la plaza principal. ||Los servicios son muy completos, ventilador de techo, electrodom칠sticos y cocina a disposici칩n y con todos los utensillos, Directv y un WIFI que anda b치rbaro! (Algo muy raro para la zona). ||La caba침a es excelente, con todas las comodidades del siglo XXI, sal칤s afuera y domina la naturaleza, es hermoso. ||Los due침os son muy atentos a las necesidades y macanud칤simos. ||Definitivamente para volver!",
            "review_link": "https://www.tripadvisor.es/ShowUserReviews-g3205091-d16877803-r718918400?m=68573&staydates=2026_02_15_2026_02_16&uguests=1_2_0&supdv=desktop&supuc=US&supul=en",
            "review_rating": "5",
            "review_date": "16/10/2019"
        },
        {
            "autor_name": "thesalvation 5555",
            "autor_image": "https://lh3.googleusercontent.com/a-/ALV-UjV8-mI20YQWePmsMVa0gn4dhWIWzHtDJeZNlAAjp4p9nLWYO-yP=s120-c-rp-mo-br100",
            "review_text": null,
            "review_link": "https://www.google.com/maps/reviews/data=!4m8!14m7!1m6!2m5!1sChZDSUhNMG9nS0VJQ0FnSUNVMGRiUFVnEAE!2m1!1s0x0:0xe7f57694b5338ff2!3m1!1s2@1:CIHM0ogKEICAgICU0dbPUg%7CCgwIjvbu6QUQsNv_qAE%7C?hl=en",
            "review_rating": "5",
            "review_date": "27/07/2019"
        },
        {
            "autor_name": "Renzo Martinez",
            "autor_image": "https://lh3.googleusercontent.com/a-/ALV-UjVCCwWVAyb5M0oUCIAdk4JwtYOpyN5-f2ZewFBWZdFTa-bNq4j7AA=s120-c-rp-mo-ba4-br100",
            "review_text": "Incre칤blemente precioso. Un lugar hermoso, al cual volveremos en el verano!!",
            "review_link": "https://www.google.com/maps/reviews/data=!4m8!14m7!1m6!2m5!1sChdDSUhNMG9nS0VJQ0FnSUNVZ1lmUmpBRRAB!2m1!1s0x0:0xe7f57694b5338ff2!3m1!1s2@1:CIHM0ogKEICAgICUgYfRjAE%7CCgwIt7Xo6QUQuMWBtwM%7C?hl=en",
            "review_rating": "5",
            "review_date": "25/07/2019"
        },
        {
            "autor_name": "Ramiro Barria",
            "autor_image": "https://lh3.googleusercontent.com/a-/ALV-UjWv2LSpvE_2ysGzGDdaIqEk44Bohf3uQYsbfRTViMYXZigxjN0=s120-c-rp-mo-br100",
            "review_text": "Es muy bueno, lo que le veo muy malo es la escalera, esta muy empinada y de echo mi hermanita de 3 a침os se cay칩. Si arreglaran eso daria 5 estrellas",
            "review_link": "https://www.google.com/maps/reviews/data=!4m8!14m7!1m6!2m5!1sChZDSUhNMG9nS0VJQ0FnSUNZLV9mbklREAE!2m1!1s0x0:0xe7f57694b5338ff2!3m1!1s2@1:CIHM0ogKEICAgICY-_fnIQ%7CCgwIoJGV6QUQ6Iet6AI%7C?hl=en",
            "review_rating": "3",
            "review_date": "10/07/2019"
        },
        {
            "autor_name": "Fernando Rodriguez",
            "autor_image": "https://lh3.googleusercontent.com/a-/ALV-UjWWuWKL_RabPBz-1UH4Ls8tH11oEfONro-oqS34K_XFerAqmReSSQ=s120-c-rp-mo-ba3-br100",
            "review_text": null,
            "review_link": "https://www.google.com/maps/reviews/data=!4m8!14m7!1m6!2m5!1sChdDSUhNMG9nS0VJQ0FnSURFdTlQcl9nRRAB!2m1!1s0x0:0xe7f57694b5338ff2!3m1!1s2@1:CIHM0ogKEICAgIDEu9Pr_gE%7CCgwIw4-v6AUQoO_wsAE%7C?hl=en",
            "review_rating": "5",
            "review_date": "20/06/2019"
        },
        {
            "autor_name": "Diego Quintun",
            "autor_image": "https://lh3.googleusercontent.com/a/ACg8ocKT0S64pO099n_qJnL7oI82frJBv4r-9Ggu0zBgOg4BMcvOQg=s120-c-rp-mo-br100",
            "review_text": null,
            "review_link": "https://www.google.com/maps/reviews/data=!4m8!14m7!1m6!2m5!1sChZDSUhNMG9nS0VJQ0FnSURZdDl2LVFREAE!2m1!1s0x0:0xe7f57694b5338ff2!3m1!1s2@1:CIHM0ogKEICAgIDYt9v-QQ%7CCgwI4uGr5wUQ2PSFqQI%7C?hl=en",
            "review_rating": "5",
            "review_date": "26/05/2019"
        },
        {
            "autor_name": "Marta Irigoyen",
            "autor_image": "https://lh3.googleusercontent.com/a/ACg8ocLfasCPuY6bKpLNtm9lTaOniwE6oHzPRutK-t_0MXFg23xtbw=s120-c-rp-mo-br100",
            "review_text": null,
            "review_link": "https://www.google.com/maps/reviews/data=!4m8!14m7!1m6!2m5!1sChdDSUhNMG9nS0VJQ0FnSURZdlpHWDlRRRAB!2m1!1s0x0:0xe7f57694b5338ff2!3m1!1s2@1:CIHM0ogKEICAgIDYvZGX9QE%7CCgwIjb6F5wUQ0LH-5QI%7C?hl=en",
            "review_rating": "5",
            "review_date": "19/05/2019"
        },
        {
            "autor_name": "mercedes andreo",
            "autor_image": "https://lh3.googleusercontent.com/a-/ALV-UjWqFGp2HTtPZzZXwEv6sQED1AjYSJTSl3v-d5eecf6qCdLfFrlB=s120-c-rp-mo-ba3-br100",
            "review_text": "Lugar super relajante y con anfitriones amables !recomendable",
            "review_link": "https://www.google.com/maps/reviews/data=!4m8!14m7!1m6!2m5!1sChZDSUhNMG9nS0VJQ0FnSUNZaV9YT2ZBEAE!2m1!1s0x0:0xe7f57694b5338ff2!3m1!1s2@1:CIHM0ogKEICAgICYi_XOfA%7CCgwIlbnp5QUQiP7TpQM%7C?hl=en",
            "review_rating": "5",
            "review_date": "19/04/2019"
        },
        {
            "autor_name": "Irma Elisa Gonzalez",
            "autor_image": "https://lh3.googleusercontent.com/a-/ALV-UjXfMXMHLevBNU6YHAAQPEhzlZJVWwFx0Qn8WcKkEE4ruwkONFhFWA=s120-c-rp-mo-br100",
            "review_text": "Bello!. Excelente atenci칩n.",
            "review_link": "https://www.google.com/maps/reviews/data=!4m8!14m7!1m6!2m5!1sChZDSUhNMG9nS0VJQ0FnSUNvbDYyY0R3EAE!2m1!1s0x0:0xe7f57694b5338ff2!3m1!1s2@1:CIHM0ogKEICAgICol62cDw%7CCgwImoL14wUQyKm76gI%7C?hl=en",
            "review_rating": "4",
            "review_date": "04/03/2019"
        },
        {
            "autor_name": "Fabian Falco",
            "autor_image": "https://lh3.googleusercontent.com/a-/ALV-UjXR8e5Vv0v8d3vaNMOyMQkRAbzSzjtKti4g84d94d9RHyVdsQnU-g=s120-c-rp-mo-ba4-br100",
            "review_text": "Muy lindas",
            "review_link": "https://www.google.com/maps/reviews/data=!4m8!14m7!1m6!2m5!1sChZDSUhNMG9nS0VJQ0FnSUNvdll5WmV3EAE!2m1!1s0x0:0xe7f57694b5338ff2!3m1!1s2@1:CIHM0ogKEICAgICovYyZew%7CCgwI1vTK4wUQoKya4gE%7C?hl=en",
            "review_rating": "5",
            "review_date": "24/02/2019"
        },
        {
            "autor_name": "Vanessa Montecino",
            "autor_image": "https://lh3.googleusercontent.com/a-/ALV-UjUUhHRbIB2uglPuOsTzlicc8uj0WFb1nS5RkFTxWHf9NGcBopYBDg=s120-c-rp-mo-ba4-br100",
            "review_text": "Un lugar super lindo, agradable, c칩modo y limpio. Con wifi y direct Tv. Lugar para el guardar el auto, permiten mascotas. Heladera, cocina, horno. Todo excelente. Super recomendable. Los due침os muy amables y serviciales.",
            "review_link": "https://www.google.com/maps/reviews/data=!4m8!14m7!1m6!2m5!1sChZDSUhNMG9nS0VJQ0FnSUNvdHVqZFVREAE!2m1!1s0x0:0xe7f57694b5338ff2!3m1!1s2@1:CIHM0ogKEICAgICotujdUQ%7CCgwI4Z-W4wUQuLq3yAE%7C?hl=en",
            "review_rating": "5",
            "review_date": "14/02/2019"
        },
        {
            "autor_name": "Diego Gonzalez",
            "autor_image": "https://lh3.googleusercontent.com/a-/ALV-UjXLRuFZI2dfq6a0H1tY1vdkKsFK1GiGkEHApbTTCqZDmg93ZCLdSQ=s120-c-rp-mo-ba4-br100",
            "review_text": "Buen Precio y servicio... ;)",
            "review_link": "https://www.google.com/maps/reviews/data=!4m8!14m7!1m6!2m5!1sChZDSUhNMG9nS0VJQ0FnSUNvdUt6MkJREAE!2m1!1s0x0:0xe7f57694b5338ff2!3m1!1s2@1:CIHM0ogKEICAgICouKz2BQ%7CCgwI_crg4gUQyK7T7QE%7C?hl=en",
            "review_rating": "5",
            "review_date": "04/02/2019"
        },
        {
            "autor_name": "Barbara Ledesma",
            "autor_image": "https://lh3.googleusercontent.com/a-/ALV-UjXcisgncINccUMLXOL9UwSuBzASMKwwSqQVr4-S5gsGe93EdUwq=s120-c-rp-mo-ba4-br100",
            "review_text": "Hermosa estad칤a, un lugar perfecto con el paisaje exterior.",
            "review_link": "https://www.google.com/maps/reviews/data=!4m8!14m7!1m6!2m5!1sChZDSUhNMG9nS0VJQ0FnSURJaS11NlhBEAE!2m1!1s0x0:0xe7f57694b5338ff2!3m1!1s2@1:CIHM0ogKEICAgIDIi-u6XA%7CCgwIxPOW4gUQ8oTMrgI%7C?hl=en",
            "review_rating": "5",
            "review_date": "21/01/2019"
        },
        {
            "autor_name": "Nehuen Sola",
            "autor_image": "https://lh3.googleusercontent.com/a-/ALV-UjXp_ZBqY19-giJp3XGYBRiQH-i3u9sRwgdiLvZGEJbZh6Z3kBDS=s120-c-rp-mo-ba2-br100",
            "review_text": null,
            "review_link": "https://www.google.com/maps/reviews/data=!4m8!14m7!1m6!2m5!1sChZDSUhNMG9nS0VJQ0FnSURJX3VyalJBEAE!2m1!1s0x0:0xe7f57694b5338ff2!3m1!1s2@1:CIHM0ogKEICAgIDI_urjRA%7CCgsI_7PK4QUQlqiJOw%7C?hl=en",
            "review_rating": "5",
            "review_date": "07/01/2019"
        },
        {
            "autor_name": "Daniel Costa",
            "autor_image": "https://lh3.googleusercontent.com/a-/ALV-UjUfPLd_etKNkWtegqsvns90FlLGDXBXliesrUWtrCUEmoGl5pMSmA=s120-c-rp-mo-ba3-br100",
            "review_text": "Muy lindo lugar, todo nuevo y en buen estado.   100% recomendable",
            "review_link": "https://www.google.com/maps/reviews/data=!4m8!14m7!1m6!2m5!1sChdDSUhNMG9nS0VJQ0FnSURBbXBQQjdnRRAB!2m1!1s0x0:0xe7f57694b5338ff2!3m1!1s2@1:CIHM0ogKEICAgIDAmpPB7gE%7CCgsI2v722wUQ0Jinbw%7C?hl=en",
            "review_rating": "5",
            "review_date": "22/08/2018"
        },
        {
            "autor_name": "Caba침as La Cautiva",
            "autor_image": "https://lh3.googleusercontent.com/a-/ALV-UjVHYSrP_T5CJ5Jg7T85thKtDJqsnWcdqrUjQ8nSlZ6Bopum3A=s120-c-rp-mo-ba2-br100",
            "review_text": null,
            "review_link": "https://www.google.com/maps/reviews/data=!4m8!14m7!1m6!2m5!1sChZDSUhNMG9nS0VJQ0FnSUNBOU5fM0hnEAE!2m1!1s0x0:0xe7f57694b5338ff2!3m1!1s2@1:CIHM0ogKEICAgICA9N_3Hg%7CCgwI8q-52QUQwIiHzgM%7C?hl=en",
            "review_rating": "4",
            "review_date": "23/06/2018"
        },
        {
            "autor_name": "Patricia Quiriban",
            "autor_image": "https://lh3.googleusercontent.com/a/ACg8ocICYzBE12Ur9yhpGgtDE1EQbN_EYGPUSQhT8ULtuRziWNGJFwfj=s120-c-rp-mo-br100",
            "review_text": null,
            "review_link": "https://www.google.com/maps/reviews/data=!4m8!14m7!1m6!2m5!1sChZDSUhNMG9nS0VJQ0FnSUNnbVlEMEZREAE!2m1!1s0x0:0xe7f57694b5338ff2!3m1!1s2@1:CIHM0ogKEICAgICgmYD0FQ%7CCgsIqLjU2AUQgOnAXA%7C?hl=en",
            "review_rating": "5",
            "review_date": "04/06/2018"
        },
        {
            "autor_name": "Carlos Gui침azu",
            "autor_image": "https://lh3.googleusercontent.com/a/ACg8ocI7SzYP6DcjbaaOw2OBHRqBQRhQC5-aLxIxYPBfIyOYt7IKPLv8=s120-c-rp-mo-ba3-br100",
            "review_text": null,
            "review_link": "https://www.google.com/maps/reviews/data=!4m8!14m7!1m6!2m5!1sChZDSUhNMG9nS0VJQ0FnSUN3em92SmVBEAE!2m1!1s0x0:0xe7f57694b5338ff2!3m1!1s2@1:CIHM0ogKEICAgICwzovJeA%7CCgwIm8q-1wUQwOqOqAI%7C?hl=en",
            "review_rating": "3",
            "review_date": "07/05/2018"
        },
        {
            "autor_name": "Luciana Correa",
            "autor_image": "https://lh3.googleusercontent.com/a-/ALV-UjWMx04k4X92EtIR9N52DB0KnOFpkSKlidfBGSYe-dmw0y2lQ6zFmA=s120-c-rp-mo-ba2-br100",
            "review_text": null,
            "review_link": "https://www.google.com/maps/reviews/data=!4m8!14m7!1m6!2m5!1sChdDSUhNMG9nS0VJQ0FnSURRNEtHYXVnRRAB!2m1!1s0x0:0xe7f57694b5338ff2!3m1!1s2@1:CIHM0ogKEICAgIDQ4KGaugE%7CCgwI5ICF1wUQgKeEmwM%7C?hl=en",
            "review_rating": "5",
            "review_date": "26/04/2018"
        },
        {
            "autor_name": "Javier Petri",
            "autor_image": "https://lh3.googleusercontent.com/a/ACg8ocLZHEjwRTzSsVa2-6Ps5TWdJSgpxwU6cQnTQZT_Y045OYnAgw=s120-c-rp-mo-ba4-br100",
            "review_text": "Lugar perfecto para parar con amigos, tiene parrilla! Muy bien precio",
            "review_link": "https://www.google.com/maps/reviews/data=!4m8!14m7!1m6!2m5!1sChZDSUhNMG9nS0VJQ0FnSUNndXZiVVB3EAE!2m1!1s0x0:0xe7f57694b5338ff2!3m1!1s2@1:CIHM0ogKEICAgICguvbUPw%7CCgwIpvnf1gUQwLXg2AI%7C?hl=en",
            "review_rating": "5",
            "review_date": "19/04/2018"
        },
        {
            "autor_name": "Ivan Braese",
            "autor_image": "https://lh3.googleusercontent.com/a-/ALV-UjXClvMFhaR5Z5W57eK4lPBCm0zqHHXz87wFTbu1nDXdWBoJtwgY8Q=s120-c-rp-mo-ba2-br100",
            "review_text": null,
            "review_link": "https://www.google.com/maps/reviews/data=!4m8!14m7!1m6!2m5!1sChdDSUhNMG9nS0VJQ0FnSUNna3QtaHFnRRAB!2m1!1s0x0:0xe7f57694b5338ff2!3m1!1s2@1:CIHM0ogKEICAgICgkt-hqgE%7CCgwI4a_D1gUQgMaPiQI%7C?hl=en",
            "review_rating": "5",
            "review_date": "13/04/2018"
        },
        {
            "autor_name": "Jorge Paredes",
            "autor_image": "https://lh3.googleusercontent.com/a-/ALV-UjX4vbKCDqoIbK3mQrVQSi4n4qx-UdqMoJh7pM5CmIc4ptgfXclC2Q=s120-c-rp-mo-ba2-br100",
            "review_text": null,
            "review_link": "https://www.google.com/maps/reviews/data=!4m8!14m7!1m6!2m5!1sChdDSUhNMG9nS0VJQ0FnSURRMnZhcGhBRRAB!2m1!1s0x0:0xe7f57694b5338ff2!3m1!1s2@1:CIHM0ogKEICAgIDQ2vaphAE%7CCgwI0Zq21QUQgN-zkwM%7C?hl=en",
            "review_rating": "5",
            "review_date": "17/03/2018"
        },
        {
            "autor_name": "El Rincon de Erica",
            "autor_image": "https://lh3.googleusercontent.com/a-/ALV-UjU0cfKxcPASyDori_1ySuVVIWwPOqP5OME0CKnRGkomUJY4s3Mc=s120-c-rp-mo-ba2-br100",
            "review_text": null,
            "review_link": "https://www.google.com/maps/reviews/data=!4m8!14m7!1m6!2m5!1sChZDSUhNMG9nS0VJQ0FnSURnMDVfa0VREAE!2m1!1s0x0:0xe7f57694b5338ff2!3m1!1s2@1:CIHM0ogKEICAgIDg05_kEQ%7CCgwIjq2M1QUQgMvjpAI%7C?hl=en",
            "review_rating": "4",
            "review_date": "09/03/2018"
        },
        {
            "autor_name": "Alicia Cristina P칠rez",
            "autor_image": "https://lh3.googleusercontent.com/a/ACg8ocKpFIBieBMJiSXJt1rl7FRBVA35iGRhRBqINEj1HBVV8Q918Q=s120-c-rp-mo-br100",
            "review_text": null,
            "review_link": "https://www.google.com/maps/reviews/data=!4m8!14m7!1m6!2m5!1sChdDSUhNMG9nS0VJQ0FnSURRXzl6V3ZnRRAB!2m1!1s0x0:0xe7f57694b5338ff2!3m1!1s2@1:CIHM0ogKEICAgIDQ_9zWvgE%7CCgsIwLnm1AUQwPjKUA%7C?hl=en",
            "review_rating": "5",
            "review_date": "02/03/2018"
        },
        {
            "autor_name": "Julian Schachter",
            "autor_image": "https://lh3.googleusercontent.com/a/ACg8ocLNZpi8FlCfoBGcpaZ2PJj_2_bEj1k6fdWRACM-DQT99FFagw=s120-c-rp-mo-br100",
            "review_text": null,
            "review_link": "https://www.google.com/maps/reviews/data=!4m8!14m7!1m6!2m5!1sChZDSUhNMG9nS0VJQ0FnSUNnOHNMZkVREAE!2m1!1s0x0:0xe7f57694b5338ff2!3m1!1s2@1:CIHM0ogKEICAgICg8sLfEQ%7CCgwI8dH90wUQwKW_yQI%7C?hl=en",
            "review_rating": "5",
            "review_date": "10/02/2018"
        },
        {
            "autor_name": "Emilia Stankiewich",
            "autor_image": "https://lh3.googleusercontent.com/a-/ALV-UjXCvMApsYo5hpXKmP69TxKDGjilagifdvRsmImty3MJQNdQ0AMy=s120-c-rp-mo-ba5-br100",
            "review_text": "Excelente mejor que lo esperado en muchos sentidos ver para creer vayan es super recomendable",
            "review_link": "https://www.google.com/maps/reviews/data=!4m8!14m7!1m6!2m5!1sChdDSUhNMG9nS0VJQ0FnSURBLU4zejhRRRAB!2m1!1s0x0:0xe7f57694b5338ff2!3m1!1s2@1:CIHM0ogKEICAgIDA-N3z8QE%7CCgwI_feu0wUQwIytswM%7C?hl=en",
            "review_rating": "5",
            "review_date": "26/01/2018"
        },
        {
            "autor_name": "Edgardo G칩mez",
            "autor_image": "https://lh3.googleusercontent.com/a-/ALV-UjUeXmuhjVRrS79H6fi1srgW2IdcDPv1N0ppIjSooVds5cW4kH6a=s120-c-rp-mo-ba4-br100",
            "review_text": "Linda caba침a. Excelente atenci칩n de los due침os. Recomendable",
            "review_link": "https://www.google.com/maps/reviews/data=!4m8!14m7!1m6!2m5!1sChZDSUhNMG9nS0VJQ0FnSURBN3J5eVh3EAE!2m1!1s0x0:0xe7f57694b5338ff2!3m1!1s2@1:CIHM0ogKEICAgIDA7ryyXw%7CCgwI_9r_0gUQwL7j0wM%7C?hl=en",
            "review_rating": "4",
            "review_date": "18/01/2018"
        },
        {
            "autor_name": "Alumin칠 SZ",
            "autor_image": "https://lh3.googleusercontent.com/a-/ALV-UjX3dWHx3YbExoW8PQlhyAIZRZn4UlSGJFsqiMB2uSr8-fDU1eQemg=s120-c-rp-mo-br100",
            "review_text": null,
            "review_link": "https://www.google.com/maps/reviews/data=!4m8!14m7!1m6!2m5!1sChZDSUhNMG9nS0VJQ0FnSUNBbjZpNWZnEAE!2m1!1s0x0:0xe7f57694b5338ff2!3m1!1s2@1:CIHM0ogKEICAgICAn6i5fg%7CCgwIks7E0gUQgLqU3wE%7C?hl=en",
            "review_rating": "5",
            "review_date": "06/01/2018"
        },
        {
            "autor_name": "Manuel Irag칲en",
            "autor_image": "https://lh3.googleusercontent.com/a-/ALV-UjVD5LJ4AGQFlcGLRHq9KuJHHST4NCTA3BjDWQxkfB8f1ZBZlLMn=s120-c-rp-mo-ba4-br100",
            "review_text": null,
            "review_link": "https://www.google.com/maps/reviews/data=!4m8!14m7!1m6!2m5!1sChZDSUhNMG9nS0VJQ0FnSURnM3RYdGFBEAE!2m1!1s0x0:0xe7f57694b5338ff2!3m1!1s2@1:CIHM0ogKEICAgIDg3tXtaA%7CCgwIgZ-HxwUQgI-XwQM%7C?hl=en",
            "review_rating": "3",
            "review_date": "03/04/2017"
        },
        {
            "autor_name": "VALERIA FRIAS",
            "autor_image": "https://lh3.googleusercontent.com/a-/ALV-UjXYWjNoMmwY2ITJJZbyn2VXqLk7lvUbBGKCeRlUYSL2wi33D_z1uA=s120-c-rp-mo-br100",
            "review_text": "Exelente ubicaci칩n y ambientes muy confortables. Mucha calidez en la atenci칩n... Un lugar HERMOSO!!!",
            "review_link": "https://www.google.com/maps/reviews/data=!4m8!14m7!1m6!2m5!1sChdDSUhNMG9nS0VJQ0FnSUNndHB1eDZ3RRAB!2m1!1s0x0:0xe7f57694b5338ff2!3m1!1s2@1:CIHM0ogKEICAgICgtpux6wE%7CCgsIjLK9xAUQwJWMRg%7C?hl=en",
            "review_rating": "5",
            "review_date": "30/01/2017"
        },
        {
            "autor_name": "Gra Fern치ndez",
            "autor_image": "https://lh3.googleusercontent.com/a/ACg8ocJsmrlJ-tQsdVGYLYNN1VECt3NPQ9pjJYGdiorqYzOHM-QjyQ=s120-c-rp-mo-br100",
            "review_text": null,
            "review_link": "https://www.google.com/maps/reviews/data=!4m8!14m7!1m6!2m5!1sChZDSUhNMG9nS0VJQ0FnSUNRb0tpNU5REAE!2m1!1s0x0:0xe7f57694b5338ff2!3m1!1s2@1:CIHM0ogKEICAgICQoKi5NQ%7CCgwIysypvAUQwN6c-AI%7C?hl=en",
            "review_rating": "5",
            "review_date": "16/07/2016"
        }
    ]
}